[
  {
    "id": 1,
    "multipleAnswers": false,
    "imageUrl": "assets/signs/Q1_image.gif",
    "description": "This warning sign tells you that you may not drive there if your vehicle is ",
    "showCorrectAnswer": false,
    "checked": false,
    "selectedAnswer": "",
    "questionType": [1, 3, 4],
    "answers": [
      {
        "key": "A",
        "description": "higher than 4.42m"
      },
      {
        "key": "B",
        "description": "longer than 4.42m"
      },
      {
        "key": "C",
        "description": "wider than 4.42m"
      }
    ],
    "correctAnswers": [
      {
        "key": "A",
        "description": "higher than 4.42m"
      }
    ]
  },
  {
    "id": 2,
    "multipleAnswers": false,
    "imageUrl": "assets/signs/Q2_image.gif",
    "description": "This road sign shows that: ",
    "showCorrectAnswer": false,
    "checked": false,
    "questionType": [1, 3, 4],
    "answers": [
      {
        "key": "A",
        "description": "You must drive there at all times if your vehicle has a GVM of 12 tons."
      },
      {
        "key": "B",
        "description": "You must drive there at all times if your vehicle has a GVM of 8 tons."
      },
      {
        "key": "C",
        "description": "If you want to you can drive there if your vehicle has a GVM of 10 tons."
      }
    ],
    "correctAnswers": [
      {
        "key": "A",
        "description": "You must drive there at all times if your vehicle has a GVM of 12 tons."
      }
    ]
  },
  {
    "id": 3,
    "multipleAnswers": false,
    "imageUrl": "",
    "description": "You may carry passengers in a vehicle that is being towed: \n1. If you only travel at 35 km/h\n2. If the vehicle that is being towed is a semi-trailerOnly \n3. if the vehicle that tows something is a tractor",
    "showCorrectAnswer": false,
    "checked": false,
    "questionType": [1, 3, 4],
    "answers": [
      {
        "key": "A",
        "description": "(1) and (2) are correct"
      },
      {
        "key": "B",
        "description": "All of the above are correct"
      },
      {
        "key": "C",
        "description": "(2) is the only correct answer"
      }
    ],
    "correctAnswers": [
      {
        "key": "C",
        "description": "(2) is the only correct answer"
      }
    ]
  },
  {
    "id": 4,
    "multipleAnswers": false,
    "imageUrl": "assets/signs/Q4_image.gif",
    "description": "What does warning sign L10 show you? ",
    "showCorrectAnswer": false,
    "checked": false,
    "questionType": [1, 3, 4, 5],
    "answers": [
      {
        "key": "A",
        "description": "Roads crossing ahead and other vehicles from the side must stop or yield at the intersection"
      },
      {
        "key": "B",
        "description": "A 4-way stop will be found ahead where the roads cross"
      },
      {
        "key": "C",
        "description": "A railway line intersects with the road that you are travelling on"
      }
    ],
    "correctAnswers": [
      {
        "key": "A",
        "description": "Roads crossing ahead and other vehicles from the side must stop or yield at the intersection"
      }
    ]
  },
  {
    "id": 5,
    "multipleAnswers": false,
    "imageUrl": "assets/signs/Q5_image.gif",
    "description": "What does this blue sign show you? ",
    "showCorrectAnswer": false,
    "checked": false,
    "questionType": [1, 3, 4, 5],
    "answers": [
      {
        "key": "A",
        "description": "You may not drive slower than 50km/h"
      },
      {
        "key": "B",
        "description": "That sign is applicable for 50 m"
      },
      {
        "key": "C",
        "description": "You may not drive faster than 50 km/h"
      }
    ],
    "correctAnswers": [
      {
        "key": "A",
        "description": "You may not drive slower than 50km/h"
      }
    ]
  },
  {
    "id": 7,
    "multipleAnswers": false,
    "imageUrl": "assets/signs/Q7_image.gif",
    "description": "This blue sign with the white arrow shows you that: ",
    "showCorrectAnswer": false,
    "checked": false,
    "questionType": [1, 3, 4, 5],
    "answers": [
      {
        "key": "A",
        "description": " You will find a one-way road ahead"
      },
      {
        "key": "B",
        "description": "You will find a free-way ahead"
      },
      {
        "key": "C",
        "description": "You must only drive straight on"
      }
    ],
    "correctAnswers": [
      {
        "key": "C",
        "description": "You must only drive straight on"
      }
    ]
  },
  {
    "id": 8,
    "multipleAnswers": false,
    "imageUrl": "assets/signs/Q8_image.gif",
    "description": "This prohibition sign indicates what? ",
    "showCorrectAnswer": false,
    "checked": false,
    "questionType": [1, 3, 4, 5],
    "answers": [
      {
        "key": "A",
        "description": "Prohibits you from using your hooter"
      },
      {
        "key": "B",
        "description": "There is a hospital ahead where you must not make a noise"
      },
      {
        "key": "C",
        "description": "You may not pick up people"
      }
    ],
    "correctAnswers": [
      {
        "key": "A",
        "description": "Prohibits you from using your hooter"
      }
    ]
  },
  {
    "id": 9,
    "multipleAnswers": false,
    "imageUrl": "assets/signs/Q9_image.gif",
    "description": "This triangle shows you that:",
    "showCorrectAnswer": false,
    "checked": false,
    "questionType": [1, 3, 4, 5],
    "answers": [
      {
        "key": "A",
        "description": "There is a special lane for cyclists"
      },
      {
        "key": "B",
        "description": " No cyclist are allowed there"
      },
      {
        "key": "C",
        "description": "You must be on the lookout for cyclist"
      }
    ],
    "correctAnswers": [
      {
        "key": "C",
        "description": "You must be on the lookout for cyclist"
      }
    ]
  },
  {
    "id": 10,
    "multipleAnswers": false,
    "imageUrl": "assets/signs/Q10_image.gif",
    "description": "This warning sign indicates: ",
    "showCorrectAnswer": false,
    "checked": false,
    "questionType": [1, 3, 4, 5],
    "answers": [
      {
        "key": "A",
        "description": "Severe winds are common in this area"
      },
      {
        "key": "B",
        "description": "The road Is slippery"
      },
      {
        "key": "C",
        "description": "The road is untarred"
      }
    ],
    "correctAnswers": [
      {
        "key": "B",
        "description": "The road Is slippery"
      }
    ]
  },
  {
    "id": 11,
    "multipleAnswers": false,
    "imageUrl": "assets/signs/Q11_image.gif",
    "description": "What does sign stop sign tell you? ",
    "showCorrectAnswer": false,
    "checked": false,
    "questionType": [1, 3, 4, 5],
    "answers": [
      {
        "key": "A",
        "description": "It is the same as a yield sign and you can proceed without stopping"
      },
      {
        "key": "B",
        "description": "Makes sure that it is safe, wait until all traffic has departed and then drive on"
      },
      {
        "key": "C",
        "description": "Stop and drive when it is safe to do so in the sequence that vehicles stopped at the stop line"
      }
    ],
    "correctAnswers": [
      {
        "key": "C",
        "description": "Stop and drive when it is safe to do so in the sequence that vehicles stopped at the stop line"
      }
    ]
  },
  {
    "id": 12,
    "multipleAnswers": false,
    "imageUrl": "",
    "description": "You may not obtain a learners license if \n\n (i) you already have a license that authorizes the driving of the same vehicle class \n (ii) you are declared unfit to obtain a driving license for a certain period and period still prevails \n (iii) you license was suspended temporarily and the suspension has not yet expired \n\n SELECT THE CORRECT COMBINATION",
    "showCorrectAnswer": false,
    "checked": false,
    "questionType": [1, 3, 4, 5],
    "answers": [
      {
        "key": "A",
        "description": "(i) only is correct"
      },
      {
        "key": "B",
        "description": "(ii) and (iii) only are correct"
      },
      {
        "key": "C",
        "description": "(i), (ii) and (iii) are correct"
      }
    ],
    "correctAnswers": [
      {
        "key": "C",
        "description": "(i), (ii) and (iii) are correct"
      }
    ]
  },
  {
    "id": 13,
    "multipleAnswers": false,
    "imageUrl": "",
    "description": "The only instance where you may stop on a freeway is...",
    "showCorrectAnswer": false,
    "checked": false,
    "questionType": [1, 3, 4, 5],
    "answers": [
      {
        "key": "A",
        "description": "To obey a road traffic sign"
      },
      {
        "key": "B",
        "description": "For a rest during a tiring journey"
      },
      {
        "key": "C",
        "description": "To pick up a hitchhiker"
      }
    ],
    "correctAnswers": [
      {
        "key": "A",
        "description": "To obey a road traffic sign"
      }
    ]
  },
  {
    "id": 14,
    "multipleAnswers": false,
    "imageUrl": "",
    "description": "You are not allowed to stop…",
    "showCorrectAnswer": false,
    "checked": false,
    "questionType": [1, 3, 4, 5],
    "answers": [
      {
        "key": "A",
        "description": "Where you are also not allowed to park"
      },
      {
        "key": "B",
        "description": "Opposite a vehicle where the roadway is 10 m wide"
      },
      {
        "key": "C",
        "description": "5 m from a bridge"
      }
    ],
    "correctAnswers": [
      {
        "key": "C",
        "description": "5 m from a bridge"
      }
    ]
  },
  {
    "id": 15,
    "multipleAnswers": false,
    "imageUrl": "",
    "description": "What is important with regard to the hooter of your vehicle?",
    "showCorrectAnswer": false,
    "checked": false,
    "questionType": [1, 3, 4, 5],
    "answers": [
      {
        "key": "A",
        "description": "The tone of pitch of the sound may not change"
      },
      {
        "key": "B",
        "description": "Someone must hear it from a distance of at least 45 m"
      },
      {
        "key": "C",
        "description": "You may use it to get the attention of someone that you would like to offer a lift"
      }
    ],
    "correctAnswers": [
      {
        "key": "A",
        "description": "The tone of pitch of the sound may not change"
      }
    ]
  },
  {
    "id": 16,
    "multipleAnswers": false,
    "imageUrl": "",
    "description": "When you were involved in an accident you…\n\n (i) Must immediately stop your vehicle\n (ii) Must determine the damage to the vehicle\n (iii) May refuse to give your name and address to anybody except to the police \n\n SELECT THE CORRECT COMBINATION",
    "showCorrectAnswer": false,
    "checked": false,
    "questionType": [1, 3, 4],
    "answers": [
      {
        "key": "A",
        "description": "(i) and (ii) only are correct"
      },
      {
        "key": "B",
        "description": "(ii) only is correct"
      },
      {
        "key": "C",
        "description": "All of the above are correct"
      }
    ],
    "correctAnswers": [
      {
        "key": "A",
        "description": "(i) and (ii) only are correct"
      }
    ]
  },
  {
    "id": 17,
    "multipleAnswers": false,
    "imageUrl": "",
    "description": "When you drive…",
    "showCorrectAnswer": false,
    "checked": false,
    "questionType": [1, 3, 4],
    "answers": [
      {
        "key": "A",
        "description": "You must have two hands on the steering wheel"
      },
      {
        "key": "B",
        "description": "Your vision of the road and the traffic must be unobstructed"
      },
      {
        "key": "C",
        "description": "You must wear shoes with rubber soles"
      }
    ],
    "correctAnswers": [
      {
        "key": "B",
        "description": "Your vision of the road and the traffic must be unobstructed"
      }
    ]
  },
  {
    "id": 18,
    "multipleAnswers": false,
    "imageUrl": "assets/signs/motor-vehicle-controls.jpg",
    "description": "When turning, use…",
    "showCorrectAnswer": false,
    "checked": false,
    "questionType": [1, 3],
    "answers": [
      {
        "key": "A",
        "description": "Number 4"
      },
      {
        "key": "B",
        "description": "Number 5"
      },
      {
        "key": "C",
        "description": "Number 10"
      }
    ],
    "correctAnswers": [
      {
        "key": "A",
        "description": "Number 4"
      }
    ]
  },
  {
    "id": 19,
    "multipleAnswers": false,
    "imageUrl": "assets/signs/motor-vehicle-controls.jpg",
    "description": "To stop, use…",
    "showCorrectAnswer": false,
    "checked": false,
    "questionType": [1, 3],
    "answers": [
      {
        "key": "A",
        "description": "Number 9"
      },
      {
        "key": "B",
        "description": "Number 8"
      },
      {
        "key": "C",
        "description": "Number 7"
      }
    ],
    "correctAnswers": [
      {
        "key": "A",
        "description": "Number 9"
      }
    ]
  },
  {
    "id": 20,
    "multipleAnswers": false,
    "imageUrl": "assets/signs/motor-vehicle-controls.jpg",
    "description": "To ensure your parked vehicle does not move, use…",
    "showCorrectAnswer": false,
    "checked": false,
    "questionType": [1, 3],
    "answers": [
      {
        "key": "A",
        "description": "Number 7"
      },
      {
        "key": "B",
        "description": "Number 8"
      },
      {
        "key": "C",
        "description": "Number 9"
      }
    ],
    "correctAnswers": [
      {
        "key": "A",
        "description": "Number 7"
      }
    ]
  },
  {
    "id": 21,
    "multipleAnswers": false,
    "imageUrl": "assets/signs/motor-vehicle-controls.jpg",
    "description": "What is number 2 used for?",
    "showCorrectAnswer": false,
    "checked": false,
    "questionType": [1, 3],
    "answers": [
      {
        "key": "A",
        "description": "To clear the windscreen of any water"
      },
      {
        "key": "B",
        "description": "To warn other road users that you are approaching"
      },
      {
        "key": "C",
        "description": "To warn other road users that you are about to turn"
      }
    ],
    "correctAnswers": [
      {
        "key": "A",
        "description": "To clear the windscreen of any water"
      }
    ]
  },
  {
    "id": 22,
    "multipleAnswers": false,
    "imageUrl": "assets/signs/motor-vehicle-controls.jpg",
    "description": "Number (x) is not found in an automatic vehicle",
    "showCorrectAnswer": false,
    "checked": false,
    "questionType": [1, 3],
    "answers": [
      {
        "key": "A",
        "description": "Number 10"
      },
      {
        "key": "B",
        "description": "Number 9"
      },
      {
        "key": "C",
        "description": "Number 8"
      }
    ],
    "correctAnswers": [
      {
        "key": "C",
        "description": "Number 8"
      }
    ]
  },
  {
    "id": 23,
    "multipleAnswers": false,
    "imageUrl": "",
    "description": "The distance that is required for a driver of a motor vehicle to stop is:\n\n (i) Longer on a wet road than on a dry road.\n (ii) Longer if the vehicle is traveling at a higher speed.\n (iii) Longer if the vehicle is loaded. \n\n SELECT THE CORRECT COMBINATION",
    "showCorrectAnswer": false,
    "checked": false,
    "questionType": [1, 3, 4],
    "answers": [
      {
        "key": "A",
        "description": "None of the above is correct."
      },
      {
        "key": "B",
        "description": "only (i) is correct."
      },
      {
        "key": "C",
        "description": "All of the above are correct"
      }
    ],
    "correctAnswers": [
      {
        "key": "C",
        "description": "All of the above are correct"
      }
    ]
  },
  {
    "id": 24,
    "multipleAnswers": false,
    "imageUrl": "",
    "description": "The maximum distance between two vehicles being towed is:",
    "showCorrectAnswer": false,
    "checked": false,
    "questionType": [1, 3],
    "answers": [
      {
        "key": "A",
        "description": "1.8m"
      },
      {
        "key": "B",
        "description": "3.5m"
      },
      {
        "key": "C",
        "description": "2.5m"
      }
    ],
    "correctAnswers": [
      {
        "key": "B",
        "description": "3.5m"
      }
    ]
  },
  {
    "id": 25,
    "multipleAnswers": false,
    "imageUrl": "",
    "description": "Which is allowed when towing another vehicle ? \n\n1. A motor car tows another motorcar with a rope and drives 40km/h\n2. You tow another vehicle with a tow bar \n3. A tractor tows a trailer with 10 passengers on it at a speed of 30 km/h",
    "showCorrectAnswer": false,
    "checked": false,
    "questionType": [1, 3],
    "answers": [
      {
        "key": "A",
        "description": "(2) and (3) are only correct"
      },
      {
        "key": "B",
        "description": "(2) is only correct"
      },
      {
        "key": "C",
        "description": "All of the above"
      }
    ],
    "correctAnswers": [
      {
        "key": "A",
        "description": "(2) and (3) are only correct"
      }
    ]
  },
  {
    "id": 26,
    "multipleAnswers": false,
    "imageUrl": "",
    "description": "What is true with regard to seat belts? \n\n1. If your vehicle has seat belts in the rear , it must be worn\n2. You need not wear a seat belt when reversing \n3. Children younger than 14 years need not wear a seat belt\n4. If the front seat has a seat belt , your only passenger may not sit at the back where there is no seat belt",
    "showCorrectAnswer": false,
    "checked": false,
    "questionType": [1, 3, 4],
    "answers": [
      {
        "key": "A",
        "description": "(1) is only correct"
      },
      {
        "key": "B",
        "description": "(1), (2) and (4) are correct"
      },
      {
        "key": "C",
        "description": "All of the above are correct"
      }
    ],
    "correctAnswers": [
      {
        "key": "B",
        "description": "(1), (2) and (4) are correct"
      }
    ]
  },
  {
    "id": 27,
    "multipleAnswers": false,
    "imageUrl": "",
    "description": "If you only have a learners license for a light motor vehicle: \n\n1. There must be someone with you in the vehicle with the same class driving license\n2. You are not allowed to drive on a freeway \n3. No passengers are allowed with you in the vehicle",
    "showCorrectAnswer": false,
    "checked": false,
    "questionType": [1, 3],
    "answers": [
      {
        "key": "A",
        "description": "All of the above are correct"
      },
      {
        "key": "B",
        "description": "Only (1) is correct"
      },
      {
        "key": "C",
        "description": "Only (1) and (2) are correct"
      }
    ],
    "correctAnswers": [
      {
        "key": "B",
        "description": "Only (1) is correct"
      }
    ]
  },
  {
    "id": 28,
    "multipleAnswers": false,
    "imageUrl": "assets/signs/Q28_image.gif",
    "description": "This road sign shows you that:",
    "showCorrectAnswer": false,
    "checked": false,
    "questionType": [1, 3],
    "answers": [
      {
        "key": "A",
        "description": "The area is motor car taxis only"
      },
      {
        "key": "B",
        "description": "You must drive there"
      },
      {
        "key": "C",
        "description": "You can drive there if you wish"
      }
    ],
    "correctAnswers": [
      {
        "key": "B",
        "description": "You must drive there"
      }
    ]
  },
  {
    "id": 29,
    "multipleAnswers": false,
    "imageUrl": "assets/signs/Q29_image.gif",
    "description": "This sign forbids:",
    "showCorrectAnswer": false,
    "checked": false,
    "questionType": [1, 3],
    "answers": [
      {
        "key": "A",
        "description": "Minibuses to drive past this sign"
      },
      {
        "key": "B",
        "description": "Minibuses to pick up passengers"
      },
      {
        "key": "C",
        "description": "All motor vehicles to drive past this sign"
      }
    ],
    "correctAnswers": [
      {
        "key": "A",
        "description": "Minibuses to drive past this sign"
      }
    ]
  },
  {
    "id": 30,
    "multipleAnswers": false,
    "imageUrl": "",
    "description": "The lights of your vehicle parked on a public road between sunset and sunrise need not kept lite when the vehicle is parked: \n\n1. 10 km form a lighted street lamp\n2. Next to the roadway of the road \n3. In a demarcated parked area",
    "showCorrectAnswer": false,
    "checked": false,
    "questionType": [1, 3],
    "answers": [
      {
        "key": "A",
        "description": "Only (i) and (iii) are correct"
      },
      {
        "key": "B",
        "description": "All of the above are correct"
      },
      {
        "key": "C",
        "description": "Only (ii) and (iii) are correct"
      }
    ],
    "correctAnswers": [
      {
        "key": "B",
        "description": "All of the above are correct"
      }
    ]
  },
  {
    "id": 31,
    "multipleAnswers": false,
    "imageUrl": "assets/signs/Q31_image.gif",
    "description": "This sign indicates that you:",
    "showCorrectAnswer": false,
    "checked": false,
    "questionType": [1],
    "answers": [
      {
        "key": "A",
        "description": "May not park there for more than 3 hours"
      },
      {
        "key": "B",
        "description": "Are only allowed to drive there between 06:00 and 09:00"
      },
      {
        "key": "C",
        "description": "May not drive there between 06:00 and 09:00"
      }
    ],
    "correctAnswers": [
      {
        "key": "C",
        "description": "May not drive there between 06:00 and 09:00"
      }
    ]
  },
  {
    "id": 32,
    "multipleAnswers": false,
    "imageUrl": "",
    "description": "It is illegal when you drive and a passenger:",
    "showCorrectAnswer": false,
    "checked": false,
    "questionType": [1],
    "answers": [
      {
        "key": "A",
        "description": "Rides on the bumper of your vehicle"
      },
      {
        "key": "B",
        "description": "Fiddles with the radio's volume knob"
      },
      {
        "key": "C",
        "description": "Sits directly behind you when you only have a learner's license"
      }
    ],
    "correctAnswers": [
      {
        "key": "A",
        "description": "Rides on the bumper of your vehicle"
      }
    ]
  },
  {
    "id": 33,
    "multipleAnswers": false,
    "imageUrl": "assets/signs/Q33_image.gif",
    "description": "This sign shows you that:",
    "showCorrectAnswer": false,
    "checked": false,
    "questionType": [1],
    "answers": [
      {
        "key": "A",
        "description": "You must use that part of the road"
      },
      {
        "key": "B",
        "description": "There is parking for motor cars there"
      },
      {
        "key": "C",
        "description": "You can use that part of the road if you wish"
      }
    ],
    "correctAnswers": [
      {
        "key": "C",
        "description": "You can use that part of the road if you wish"
      }
    ]
  },
  {
    "id": 34,
    "multipleAnswers": false,
    "imageUrl": "",
    "description": "The tread pattern of your vehicle's tyres may not be less than:",
    "showCorrectAnswer": false,
    "checked": false,
    "questionType": [1],
    "answers": [
      {
        "key": "A",
        "description": "1.5mm"
      },
      {
        "key": "B",
        "description": "1mm"
      },
      {
        "key": "C",
        "description": "0.75mm"
      }
    ],
    "correctAnswers": [
      {
        "key": "B",
        "description": "1mm"
      }
    ]
  },
  {
    "id": 35,
    "multipleAnswers": false,
    "imageUrl": "assets/signs/Q35_image.gif",
    "description": "TThis road sign shows you that:",
    "showCorrectAnswer": false,
    "checked": false,
    "questionType": [1],
    "answers": [
      {
        "key": "A",
        "description": "No taxis may drive there"
      },
      {
        "key": "B",
        "description": "You may not park your motorcar there"
      },
      {
        "key": "C",
        "description": "No motorcars may drive there"
      }
    ],
    "correctAnswers": [
      {
        "key": "C",
        "description": "No motorcars may drive there"
      }
    ]
  },
  {
    "id": 36,
    "multipleAnswers": false,
    "imageUrl": "assets/signs/motor-vehicle-controls.jpg",
    "description": "To select a gear, you must use number?",
    "showCorrectAnswer": false,
    "checked": false,
    "questionType": [1],
    "answers": [
      {
        "key": "A",
        "description": "7 and 9"
      },
      {
        "key": "B",
        "description": "6 and 8"
      },
      {
        "key": "C",
        "description": "5 and 8"
      }
    ],
    "correctAnswers": [
      {
        "key": "B",
        "description": "6 and 8"
      }
    ]
  },
  {
    "id": 37,
    "multipleAnswers": false,
    "imageUrl": "assets/signs/motor-vehicle-controls.jpg",
    "description": "To accelerate your vehicle, you must use number:",
    "showCorrectAnswer": false,
    "checked": false,
    "questionType": [1],
    "answers": [
      {
        "key": "A",
        "description": "6"
      },
      {
        "key": "B",
        "description": "8"
      },
      {
        "key": "C",
        "description": "10"
      }
    ],
    "correctAnswers": [
      {
        "key": "C",
        "description": "10"
      }
    ]
  },
  {
    "id": 38,
    "multipleAnswers": false,
    "imageUrl": "assets/signs/motor-vehicle-controls.jpg",
    "description": "What controls must you use when you are going to turn sharp?",
    "showCorrectAnswer": false,
    "checked": false,
    "questionType": [1],
    "answers": [
      {
        "key": "A",
        "description": "1,3,4,5,6,8,9 and 10 only"
      },
      {
        "key": "B",
        "description": "1,3,5,6, and 8 only"
      },
      {
        "key": "C",
        "description": "3,4,5,9, and 10 only"
      }
    ],
    "correctAnswers": [
      {
        "key": "A",
        "description": "1,3,4,5,6,8,9 and 10 only"
      }
    ]
  }
]
